README.md
setup.py
gizwits/__init__.py
gizwits.egg-info/PKG-INFO
gizwits.egg-info/SOURCES.txt
gizwits.egg-info/dependency_links.txt
gizwits.egg-info/requires.txt
gizwits.egg-info/top_level.txt