Metadata-Version: 1.1
Name: gizwits
Version: 0.0.1
Summary: Git & Markdown & Web based wiki system
Home-page: https://github.com/menduo/gizwits
Author: menduo
Author-email: shimenduo@gmail.com
License: MIT
Keywords: gizwits,wiki,git,markdown
Platform: any
Classifier: Intended Audience :: Developers
Classifier: License :: OSI Approved :: MIT License
Classifier: Operating System :: OS Independent
Classifier: Programming Language :: Python
Classifier: Programming Language :: Python :: 2
Classifier: Programming Language :: Python :: 2.6
Classifier: Programming Language :: Python :: 2.7
Classifier: Programming Language :: Python :: 3
Classifier: Programming Language :: Python :: 3.3
Classifier: Programming Language :: Python :: 3.4
Classifier: Programming Language :: Python :: 3.5
Classifier: Topic :: Internet :: WWW/HTTP :: Dynamic Content
Classifier: Topic :: Software Development :: Libraries :: Python Modules
